[
    {
        "player_id": 1,
        "firstName": "Lebron",
        "lastName": "James", 
        "gameId": 1,
        "points": 25,
        "rebounds": 10,
        "assists": 10,
        "steals": 2,
        "turnovers": 3,
        "blocks": 1,
        "personalFouls": 2
    },
    {
        "player_id": 2,
        "firstName": "Anthony",
        "lastName": "Davis",
        "gameId": 1,
        "points": 30,
        "rebounds": 12,
        "assists": 5,
        "steals": 1,
        "turnovers": 2,
        "blocks": 3,
        "personalFouls": 1
    },
    {
        "player_id": 3,
        "firstName": "James",
        "lastName": "Harden",
        "gameId": 1,
        "points": 35,
        "rebounds": 5,
        "assists": 10,
        "steals": 2,
        "turnovers": 4,
        "blocks": 0,
        "personalFouls": 3
    },
    {
        "player_id": 4,
        "firstName": "Kevin",
        "lastName": "Durant",
        "gameId": 1,
        "points": 40,
        "rebounds": 8,
        "assists": 5,
        "steals": 1,
        "turnovers": 3,
        "blocks": 2,
        "personalFouls": 2
    },
    {
        "player_id": 5,
        "firstName": "Kyrie",
        "lastName": "Irving",
        "gameId": 1,
        "points": 30,
        "rebounds": 5,
        "assists": 10,
        "steals": 2,
        "turnovers": 3,
        "blocks": 0,
        "personalFouls": 2
    },
    {
        "player_id": 6,
        "firstName": "Stephen",
        "lastName": "Curry",
        "gameId": 1,
        "points": 35,
        "rebounds": 5,
        "assists": 10,
        "steals": 2,
        "turnovers": 3,
        "blocks": 0,
        "personalFouls": 2
    },
    {
        "player_id": 7,
        "firstName": "Klay",
        "lastName": "Thompson",
        "gameId": 1,
        "points": 30,
        "rebounds": 5,
        "assists": 5,
        "steals": 2,
        "turnovers": 3,
        "blocks": 0,
        "personalFouls": 2
    },
    {
        "player_id": 8,
        "firstName": "Draymond",
        "lastName": "Green",
        "gameId": 1,
        "points": 15,
        "rebounds": 10,
        "assists": 10,
        "steals": 2,
        "turnovers": 3,
        "blocks": 1,
        "personalFouls": 2
    },
    {
        "player_id": 9,
        "firstName": "kawhi",
        "lastName": "Leonard",
        "gameId": 1,
        "points": 30,
        "rebounds": 10,
        "assists": 5,
        "steals": 2,
        "turnovers": 3,
        "blocks": 1,
        "personalFouls": 2
    },
    {
        "player_id": 10,
        "firstName": "Paul",
        "lastName": "George",
        "gameId": 1,
        "points": 30,
        "rebounds": 10,
        "assists": 5,
        "steals": 2,
        "turnovers": 3,
        "blocks": 1,
        "personalFouls": 2
    },
    {
        "player_id": 1,
        "firstName": "Lebron",
        "lastName": "James", 
        "gameId": 2,
        "points": 24,
        "rebounds": 11,
        "assists": 5,
        "steals": 1,
        "turnovers": 2,
        "blocks": 3,
        "personalFouls": 4
    },
    {
        "player_id": 2,
        "firstName": "Anthony",
        "lastName": "Davis",
        "gameId": 2,
        "points": 14,
        "rebounds": 9,
        "assists": 4,
        "steals": 0,
        "turnovers": 3,
        "blocks": 4,
        "personalFouls": 5
    },
    {
        "player_id": 3,
        "firstName": "James",
        "lastName": "Harden",
        "gameId": 2,
        "points": 24,
        "rebounds": 6,
        "assists": 5,
        "steals": 4,
        "turnovers": 6,
        "blocks": 1,
        "personalFouls": 4
    },
    {
        "player_id": 4,
        "firstName": "Kevin",
        "lastName": "Durant",
        "gameId": 2,
        "points": 28,
        "rebounds": 10,
        "assists": 3,
        "steals": 3,
        "turnovers": 4,
        "blocks": 1,
        "personalFouls": 3
    },
    {
        "player_id": 5,
        "firstName": "Kyrie",
        "lastName": "Irving",
        "gameId": 2,
        "points": 18,
        "rebounds": 3,
        "assists": 14,
        "steals": 5,
        "turnovers": 2,
        "blocks": 0,
        "personalFouls": 3
    },
    {
        "player_id": 6,
        "firstName": "Stephen",
        "lastName": "Curry",
        "gameId": 2,
        "points": 28,
        "rebounds": 4,
        "assists": 9,
        "steals": 4,
        "turnovers": 2,
        "blocks": 1,
        "personalFouls": 4
    },
    {
        "player_id": 7,
        "firstName": "Klay",
        "lastName": "Thompson",
        "gameId": 2,
        "points": 21,
        "rebounds": 6,
        "assists": 4,
        "steals": 5,
        "turnovers": 4,
        "blocks": 1,
        "personalFouls": 4
    },
    {
        "player_id": 8,
        "firstName": "Draymond",
        "lastName": "Green",
        "gameId": 2,
        "points": 21,
        "rebounds": 15,
        "assists": 5,
        "steals": 3,
        "turnovers": 6,
        "blocks": 2,
        "personalFouls": 5
    },
    {
        "player_id": 9,
        "firstName": "kawhi",
        "lastName": "Leonard",
        "gameId": 2,
        "points": 25,
        "rebounds": 7,
        "assists": 3,
        "steals": 4,
        "turnovers": 1,
        "blocks": 1,
        "personalFouls": 3
    },
    {
        "player_id": 10,
        "firstName": "Paul",
        "lastName": "George",
        "gameId": 2,
        "points": 14,
        "rebounds": 6,
        "assists": 8,
        "steals": 4,
        "turnovers": 2,
        "blocks": 1,
        "personalFouls": 3
    },
    {
        "player_id": 1,
        "firstName": "Lebron",
        "lastName": "James", 
        "gameId": 3,
        "points": 36,
        "rebounds": 14,
        "assists": 7,
        "steals": 3,
        "turnovers": 4,
        "blocks": 2,
        "personalFouls": 5
    },
    {
        "player_id": 2,
        "firstName": "Anthony",
        "lastName": "Davis",
        "gameId": 3,
        "points": 24,
        "rebounds": 15,
        "assists": 3,
        "steals": 1,
        "turnovers": 2,
        "blocks": 2,
        "personalFouls": 4
    },
    {
        "player_id": 3,
        "firstName": "James",
        "lastName": "Harden",
        "gameId": 3,
        "points": 31,
        "rebounds": 7,
        "assists": 3,
        "steals": 2,
        "turnovers": 3,
        "blocks": 2,
        "personalFouls": 3
    },
    {
        "player_id": 4,
        "firstName": "Kevin",
        "lastName": "Durant",
        "gameId": 3,
        "points": 17,
        "rebounds": 7,
        "assists": 5,
        "steals": 2,
        "turnovers": 3,
        "blocks": 2,
        "personalFouls": 4
    },
    {
        "player_id": 5,
        "firstName": "Kyrie",
        "lastName": "Irving",
        "gameId": 3,
        "points": 27,
        "rebounds": 4,
        "assists": 6,
        "steals": 3,
        "turnovers": 3,
        "blocks": 1,
        "personalFouls": 4
    },
    {
        "player_id": 6,
        "firstName": "Stephen",
        "lastName": "Curry",
        "gameId": 3,
        "points": 28,
        "rebounds": 6,
        "assists": 11,
        "steals": 5,
        "turnovers": 3,
        "blocks": 0,
        "personalFouls": 3
    },
    {
        "player_id": 7,
        "firstName": "Klay",
        "lastName": "Thompson",
        "gameId": 3,
        "points": 27,
        "rebounds": 7,
        "assists": 6,
        "steals": 2,
        "turnovers": 3,
        "blocks": 2,
        "personalFouls": 5
    },
    {
        "player_id": 8,
        "firstName": "Draymond",
        "lastName": "Green",
        "gameId": 3,
        "points": 14,
        "rebounds": 10,
        "assists": 4,
        "steals": 1,
        "turnovers": 2,
        "blocks": 3,
        "personalFouls": 4
    },
    {
        "player_id": 9,
        "firstName": "kawhi",
        "lastName": "Leonard",
        "gameId": 3,
        "points": 17,
        "rebounds": 3,
        "assists": 6,
        "steals": 2,
        "turnovers": 4,
        "blocks": 0,
        "personalFouls": 5
    },
    {
        "player_id": 10,
        "firstName": "Paul",
        "lastName": "George",
        "gameId": 3,
        "points": 22,
        "rebounds": 9,
        "assists": 5,
        "steals": 2,
        "turnovers": 4,
        "blocks": 0,
        "personalFouls": 3
    },
    {
        "player_id": 1,
        "firstName": "Lebron",
        "lastName": "James", 
        "gameId": 4,
        "points": 36,
        "rebounds": 11,
        "assists": 6,
        "steals": 2,
        "turnovers": 4,
        "blocks": 2,
        "personalFouls": 5
    },
    {
        "player_id": 2,
        "firstName": "Anthony",
        "lastName": "Davis",
        "gameId": 4,
        "points": 28,
        "rebounds": 13,
        "assists": 3,
        "steals": 2,
        "turnovers": 2,
        "blocks": 3,
        "personalFouls": 4
    },
    {
        "player_id": 3,
        "firstName": "James",
        "lastName": "Harden",
        "gameId": 4,
        "points": 19,
        "rebounds": 4,
        "assists": 7,
        "steals": 3,
        "turnovers": 4,
        "blocks": 2,
        "personalFouls": 3
    },
    {
        "player_id": 4,
        "firstName": "Kevin",
        "lastName": "Durant",
        "gameId": 4,
        "points": 28,
        "rebounds": 10,
        "assists": 5,
        "steals": 2,
        "turnovers": 2,
        "blocks": 3,
        "personalFouls": 4
    },
    {
        "player_id": 5,
        "firstName": "Kyrie",
        "lastName": "Irving",
        "gameId": 4,
        "points": 28,
        "rebounds": 2,
        "assists": 7,
        "steals": 4,
        "turnovers": 5,
        "blocks": 1,
        "personalFouls": 4
    },
    {
        "player_id": 6,
        "firstName": "Stephen",
        "lastName": "Curry",
        "gameId": 4,
        "points": 37,
        "rebounds": 6,
        "assists": 11,
        "steals": 3,
        "turnovers": 4,
        "blocks": 0,
        "personalFouls": 5
    },
    {
        "player_id": 7,
        "firstName": "Klay",
        "lastName": "Thompson",
        "gameId": 4,
        "points": 19,
        "rebounds": 7,
        "assists": 6,
        "steals": 3,
        "turnovers": 2,
        "blocks": 3,
        "personalFouls": 3
    },
    {
        "player_id": 8,
        "firstName": "Draymond",
        "lastName": "Green",
        "gameId": 4,
        "points": 16,
        "rebounds": 11,
        "assists": 3,
        "steals": 1,
        "turnovers": 3,
        "blocks": 5,
        "personalFouls": 4
    },
    {
        "player_id": 9,
        "firstName": "kawhi",
        "lastName": "Leonard",
        "gameId": 4,
        "points": 34,
        "rebounds": 5,
        "assists": 6,
        "steals": 3,
        "turnovers": 3,
        "blocks": 2,
        "personalFouls": 5
    },
    {
        "player_id": 10,
        "firstName": "Paul",
        "lastName": "George",
        "gameId": 4,
        "points": 27,
        "rebounds": 4,
        "assists": 4,
        "steals": 1,
        "turnovers": 7,
        "blocks": 0,
        "personalFouls": 6
    },
    {
        "player_id": 1,
        "firstName": "Lebron",
        "lastName": "James", 
        "gameId": 5,
        "points": 31,
        "rebounds": 14,
        "assists": 10,
        "steals": 4,
        "turnovers": 2,
        "blocks": 4,
        "personalFouls": 5
    },
    {
        "player_id": 2,
        "firstName": "Anthony",
        "lastName": "Davis",
        "gameId": 5,
        "points": 15,
        "rebounds": 15,
        "assists": 2,
        "steals": 2,
        "turnovers": 1,
        "blocks": 3,
        "personalFouls": 4
    },
    {
        "player_id": 3,
        "firstName": "James",
        "lastName": "Harden",
        "gameId": 5,
        "points": 29,
        "rebounds": 7,
        "assists": 7,
        "steals": 3,
        "turnovers": 2,
        "blocks": 2,
        "personalFouls": 5
    },
    {
        "player_id": 4,
        "firstName": "Kevin",
        "lastName": "Durant",
        "gameId": 5,
        "points": 21,
        "rebounds": 13,
        "assists": 4,
        "steals": 2,
        "turnovers": 2,
        "blocks": 3,
        "personalFouls": 4
    },
    {
        "player_id": 5,
        "firstName": "Kyrie",
        "lastName": "Irving",
        "gameId": 5,
        "points": 18,
        "rebounds": 5,
        "assists": 12,
        "steals": 3,
        "turnovers": 4,
        "blocks": 1,
        "personalFouls": 4
    },
    {
        "player_id": 6,
        "firstName": "Stephen",
        "lastName": "Curry",
        "gameId": 5,
        "points": 18,
        "rebounds": 6,
        "assists": 6,
        "steals": 5,
        "turnovers": 3,
        "blocks": 0,
        "personalFouls": 3
    },
    {
        "player_id": 7,
        "firstName": "Klay",
        "lastName": "Thompson",
        "gameId": 5,
        "points": 21,
        "rebounds": 3,
        "assists": 7,
        "steals": 3,
        "turnovers": 1,
        "blocks": 3,
        "personalFouls": 3
    },
    {
        "player_id": 8,
        "firstName": "Draymond",
        "lastName": "Green",
        "gameId": 5,
        "points": 28,
        "rebounds": 11,
        "assists": 3,
        "steals": 2,
        "turnovers": 3,
        "blocks": 4,
        "personalFouls": 4
    },
    {
        "player_id": 9,
        "firstName": "kawhi",
        "lastName": "Leonard",
        "gameId": 5,
        "points": 38,
        "rebounds": 11,
        "assists": 5,
        "steals": 4,
        "turnovers": 3,
        "blocks": 2,
        "personalFouls": 5
    },
    {
        "player_id": 10,
        "firstName": "Paul",
        "lastName": "George",
        "gameId": 5,
        "points": 23,
        "rebounds": 4,
        "assists": 6,
        "steals": 3,
        "turnovers": 5,
        "blocks": 0,
        "personalFouls": 4
    }
]

